pymiele/__init__.py
pymiele/code_enum.py
pymiele/const.py
pymiele/model.py
pymiele/py.typed
pymiele/pymiele.py
pymiele-0.6.1.dist-info/licenses/LICENSE
pymiele-0.6.1.dist-info/METADATA
pymiele-0.6.1.dist-info/WHEEL
pymiele-0.6.1.dist-info/top_level.txt
pymiele-0.6.1.dist-info/RECORD
