Metadata-Version: 2.4
Name: pymiele
Version: 0.6.1
Summary: Python library for Miele integration with Home Assistant
Author-email: Ake Strandberg <ake@strandberg.eu>
License: MIT
Project-URL: Repository, https://github.com/nordicopen/pymiele
Project-URL: BugTracker, https://github.com/nordicopen/pymiele/issues
Classifier: Programming Language :: Python :: 3
Classifier: Operating System :: OS Independent
Classifier: Development Status :: 4 - Beta
Requires-Python: >=3.13.0
License-File: LICENSE
Requires-Dist: aiohttp
Dynamic: license-file
